ext4/__init__.py
ext4/_compat.py
ext4/block.py
ext4/blockdescriptor.py
ext4/directory.py
ext4/enum.py
ext4/extent.py
ext4/htree.py
ext4/inode.py
ext4/struct.py
ext4/superblock.py
ext4/volume.py
ext4/xattr.py
ext4-1.2.2.dist-info/licenses/LICENSE
ext4-1.2.2.dist-info/METADATA
ext4-1.2.2.dist-info/WHEEL
ext4-1.2.2.dist-info/top_level.txt
ext4-1.2.2.dist-info/RECORD
